vaultdweller/__init__.py
vaultdweller/client.py
vaultdweller/crypto.py
vaultdweller/exceptions.py
vaultdweller/models.py
vaultdweller/vault.py
vaultdweller-0.2.2.dist-info/METADATA
vaultdweller-0.2.2.dist-info/WHEEL
vaultdweller-0.2.2.dist-info/licenses/LICENSE
vaultdweller-0.2.2.dist-info/RECORD
