Metadata-Version: 2.4
Name: vaultdweller
Version: 0.2.2
Summary: This is the simplest client for quick work with vaultwarden.
Home-page: https://github.com/Ckoetael/vaultdweller
Author: ckoetael
Author-email: Alex Minko <ckoetael@gmail.com>
License-Expression: MIT
Project-URL: Homepage, https://github.com/Ckoetael/vaultdweller
Project-URL: Issues, https://github.com/Ckoetael/vaultdweller/issues
Classifier: Programming Language :: Python :: 3
Classifier: Operating System :: OS Independent
Requires-Python: >=3.11
License-File: LICENSE
Dynamic: author
Dynamic: home-page
Dynamic: license-file
Dynamic: requires-python
